LICENSE
MANIFEST.in
README.rst
setup.cfg
setup.py
docs/Makefile
docs/conf.py
docs/index.rst
docs/installation.rst
docs/make.bat
docs/readme.rst
docs/usage.rst
imgutils/__init__.py
imgutils/imgdims.py
imgutils/np_pil_interop.py
imgutils/palette.py
imgutils/pil_utils.py
imgutils/remapping.py
imgutils.egg-info/PKG-INFO
imgutils.egg-info/SOURCES.txt
imgutils.egg-info/dependency_links.txt
imgutils.egg-info/not-zip-safe
imgutils.egg-info/requires.txt
imgutils.egg-info/top_level.txt
tests/__init__.py
tests/test_imgutils.py