Metadata-Version: 1.1
Name: imgutils
Version: 0.1.1
Summary: Miscellaneous image utility functions.
Home-page: https://github.com/dimatura/imgutils
Author: Daniel Maturana
Author-email: dimatura@cmu.edu
License: BSD license
Keywords: imgutils
Platform: UNKNOWN
Classifier: Development Status :: 2 - Pre-Alpha
Classifier: Intended Audience :: Developers
Classifier: License :: OSI Approved :: BSD License
Classifier: Natural Language :: English
Classifier: Programming Language :: Python :: 2
Classifier: Programming Language :: Python :: 2.6
Classifier: Programming Language :: Python :: 2.7
